[{
	"ProductCode": "ProductCode 1",
	"SalesProgram": "SalesProgram 1",
	"DateFrom": "/Date(1245829659000)/",
	"DateTo": "/Date(1526284059000)/",
	"RecipeNumber": 8004.07,
	"Id": "Id 1",
	"__metadata": {
		"uri": "productRecipeSet('Id%201')",
		"type": "ZTS_MD_BP_SRV.ProductRecipe"
	}
}, {
	"ProductCode": "ProductCode 2",
	"SalesProgram": "SalesProgram 2",
	"DateFrom": "/Date(1371368859000)/",
	"DateTo": "/Date(1577346459000)/",
	"RecipeNumber": 7718.61,
	"Id": "Id 2",
	"__metadata": {
		"uri": "productRecipeSet('Id%202')",
		"type": "ZTS_MD_BP_SRV.ProductRecipe"
	}
}, {
	"ProductCode": "ProductCode 3",
	"SalesProgram": "SalesProgram 3",
	"DateFrom": "/Date(1268984859000)/",
	"DateTo": "/Date(1171439259000)/",
	"RecipeNumber": 6238.89,
	"Id": "Id 3",
	"__metadata": {
		"uri": "productRecipeSet('Id%203')",
		"type": "ZTS_MD_BP_SRV.ProductRecipe"
	}
}, {
	"ProductCode": "ProductCode 4",
	"SalesProgram": "SalesProgram 4",
	"DateFrom": "/Date(1431416859000)/",
	"DateTo": "/Date(984988059000)/",
	"RecipeNumber": 9129.76,
	"Id": "Id 4",
	"__metadata": {
		"uri": "productRecipeSet('Id%204')",
		"type": "ZTS_MD_BP_SRV.ProductRecipe"
	}
}, {
	"ProductCode": "ProductCode 5",
	"SalesProgram": "SalesProgram 5",
	"DateFrom": "/Date(1179128859000)/",
	"DateTo": "/Date(1031125659000)/",
	"RecipeNumber": 5258.55,
	"Id": "Id 5",
	"__metadata": {
		"uri": "productRecipeSet('Id%205')",
		"type": "ZTS_MD_BP_SRV.ProductRecipe"
	}
}, {
	"ProductCode": "ProductCode 6",
	"SalesProgram": "SalesProgram 6",
	"DateFrom": "/Date(1527493659000)/",
	"DateTo": "/Date(1316332059000)/",
	"RecipeNumber": 7917.8,
	"Id": "Id 6",
	"__metadata": {
		"uri": "productRecipeSet('Id%206')",
		"type": "ZTS_MD_BP_SRV.ProductRecipe"
	}
}, {
	"ProductCode": "ProductCode 7",
	"SalesProgram": "SalesProgram 7",
	"DateFrom": "/Date(1254815259000)/",
	"DateTo": "/Date(1553759259000)/",
	"RecipeNumber": 6331.07,
	"Id": "Id 7",
	"__metadata": {
		"uri": "productRecipeSet('Id%207')",
		"type": "ZTS_MD_BP_SRV.ProductRecipe"
	}
}, {
	"ProductCode": "ProductCode 8",
	"SalesProgram": "SalesProgram 8",
	"DateFrom": "/Date(1151048859000)/",
	"DateTo": "/Date(1373096859000)/",
	"RecipeNumber": 2011.34,
	"Id": "Id 8",
	"__metadata": {
		"uri": "productRecipeSet('Id%208')",
		"type": "ZTS_MD_BP_SRV.ProductRecipe"
	}
}, {
	"ProductCode": "ProductCode 9",
	"SalesProgram": "SalesProgram 9",
	"DateFrom": "/Date(1001922459000)/",
	"DateTo": "/Date(1027669659000)/",
	"RecipeNumber": 2667.09,
	"Id": "Id 9",
	"__metadata": {
		"uri": "productRecipeSet('Id%209')",
		"type": "ZTS_MD_BP_SRV.ProductRecipe"
	}
}, {
	"ProductCode": "ProductCode 10",
	"SalesProgram": "SalesProgram 10",
	"DateFrom": "/Date(1452412059000)/",
	"DateTo": "/Date(1181634459000)/",
	"RecipeNumber": 9627.19,
	"Id": "Id 10",
	"__metadata": {
		"uri": "productRecipeSet('Id%2010')",
		"type": "ZTS_MD_BP_SRV.ProductRecipe"
	}
}, {
	"ProductCode": "ProductCode 11",
	"SalesProgram": "SalesProgram 11",
	"DateFrom": "/Date(1231400861000)/",
	"DateTo": "/Date(1270799261000)/",
	"RecipeNumber": 2179.06,
	"Id": "Id 11",
	"__metadata": {
		"uri": "productRecipeSet('Id%2011')",
		"type": "ZTS_MD_BP_SRV.ProductRecipe"
	}
}, {
	"ProductCode": "ProductCode 12",
	"SalesProgram": "SalesProgram 12",
	"DateFrom": "/Date(1379922461000)/",
	"DateTo": "/Date(1017992861000)/",
	"RecipeNumber": 6523.81,
	"Id": "Id 12",
	"__metadata": {
		"uri": "productRecipeSet('Id%2012')",
		"type": "ZTS_MD_BP_SRV.ProductRecipe"
	}
}, {
	"ProductCode": "ProductCode 13",
	"SalesProgram": "SalesProgram 13",
	"DateFrom": "/Date(1067672861000)/",
	"DateTo": "/Date(1030261661000)/",
	"RecipeNumber": 1808.07,
	"Id": "Id 13",
	"__metadata": {
		"uri": "productRecipeSet('Id%2013')",
		"type": "ZTS_MD_BP_SRV.ProductRecipe"
	}
}, {
	"ProductCode": "ProductCode 14",
	"SalesProgram": "SalesProgram 14",
	"DateFrom": "/Date(1022053661000)/",
	"DateTo": "/Date(1396424861000)/",
	"RecipeNumber": 5458.54,
	"Id": "Id 14",
	"__metadata": {
		"uri": "productRecipeSet('Id%2014')",
		"type": "ZTS_MD_BP_SRV.ProductRecipe"
	}
}, {
	"ProductCode": "ProductCode 15",
	"SalesProgram": "SalesProgram 15",
	"DateFrom": "/Date(1566287261000)/",
	"DateTo": "/Date(1261554461000)/",
	"RecipeNumber": 4978.09,
	"Id": "Id 15",
	"__metadata": {
		"uri": "productRecipeSet('Id%2015')",
		"type": "ZTS_MD_BP_SRV.ProductRecipe"
	}
}, {
	"ProductCode": "ProductCode 16",
	"SalesProgram": "SalesProgram 16",
	"DateFrom": "/Date(1426751261000)/",
	"DateTo": "/Date(1288770461000)/",
	"RecipeNumber": 6595.25,
	"Id": "Id 16",
	"__metadata": {
		"uri": "productRecipeSet('Id%2016')",
		"type": "ZTS_MD_BP_SRV.ProductRecipe"
	}
}, {
	"ProductCode": "ProductCode 17",
	"SalesProgram": "SalesProgram 17",
	"DateFrom": "/Date(1176450461000)/",
	"DateTo": "/Date(1028792861000)/",
	"RecipeNumber": 2976.42,
	"Id": "Id 17",
	"__metadata": {
		"uri": "productRecipeSet('Id%2017')",
		"type": "ZTS_MD_BP_SRV.ProductRecipe"
	}
}, {
	"ProductCode": "ProductCode 18",
	"SalesProgram": "SalesProgram 18",
	"DateFrom": "/Date(1374824861000)/",
	"DateTo": "/Date(1433317661000)/",
	"RecipeNumber": 9083.51,
	"Id": "Id 18",
	"__metadata": {
		"uri": "productRecipeSet('Id%2018')",
		"type": "ZTS_MD_BP_SRV.ProductRecipe"
	}
}, {
	"ProductCode": "ProductCode 19",
	"SalesProgram": "SalesProgram 19",
	"DateFrom": "/Date(1183362461000)/",
	"DateTo": "/Date(1469519261000)/",
	"RecipeNumber": 9117.63,
	"Id": "Id 19",
	"__metadata": {
		"uri": "productRecipeSet('Id%2019')",
		"type": "ZTS_MD_BP_SRV.ProductRecipe"
	}
}, {
	"ProductCode": "ProductCode 20",
	"SalesProgram": "SalesProgram 20",
	"DateFrom": "/Date(1498117661000)/",
	"DateTo": "/Date(1574668061000)/",
	"RecipeNumber": 9041.36,
	"Id": "Id 20",
	"__metadata": {
		"uri": "productRecipeSet('Id%2020')",
		"type": "ZTS_MD_BP_SRV.ProductRecipe"
	}
}, {
	"ProductCode": "ProductCode 21",
	"SalesProgram": "SalesProgram 21",
	"DateFrom": "/Date(1342424861000)/",
	"DateTo": "/Date(1180856861000)/",
	"RecipeNumber": 5494.63,
	"Id": "Id 21",
	"__metadata": {
		"uri": "productRecipeSet('Id%2021')",
		"type": "ZTS_MD_BP_SRV.ProductRecipe"
	}
}, {
	"ProductCode": "ProductCode 22",
	"SalesProgram": "SalesProgram 22",
	"DateFrom": "/Date(1507362461000)/",
	"DateTo": "/Date(1132300061000)/",
	"RecipeNumber": 6676.24,
	"Id": "Id 22",
	"__metadata": {
		"uri": "productRecipeSet('Id%2022')",
		"type": "ZTS_MD_BP_SRV.ProductRecipe"
	}
}, {
	"ProductCode": "ProductCode 23",
	"SalesProgram": "SalesProgram 23",
	"DateFrom": "/Date(1449992861000)/",
	"DateTo": "/Date(1505461661000)/",
	"RecipeNumber": 1007.44,
	"Id": "Id 23",
	"__metadata": {
		"uri": "productRecipeSet('Id%2023')",
		"type": "ZTS_MD_BP_SRV.ProductRecipe"
	}
}, {
	"ProductCode": "ProductCode 24",
	"SalesProgram": "SalesProgram 24",
	"DateFrom": "/Date(964856861000)/",
	"DateTo": "/Date(1234079261000)/",
	"RecipeNumber": 2321.67,
	"Id": "Id 24",
	"__metadata": {
		"uri": "productRecipeSet('Id%2024')",
		"type": "ZTS_MD_BP_SRV.ProductRecipe"
	}
}, {
	"ProductCode": "ProductCode 25",
	"SalesProgram": "SalesProgram 25",
	"DateFrom": "/Date(1392450461000)/",
	"DateTo": "/Date(1325922461000)/",
	"RecipeNumber": 7906.19,
	"Id": "Id 25",
	"__metadata": {
		"uri": "productRecipeSet('Id%2025')",
		"type": "ZTS_MD_BP_SRV.ProductRecipe"
	}
}, {
	"ProductCode": "ProductCode 26",
	"SalesProgram": "SalesProgram 26",
	"DateFrom": "/Date(1456732061000)/",
	"DateTo": "/Date(1260517661000)/",
	"RecipeNumber": 5796.1,
	"Id": "Id 26",
	"__metadata": {
		"uri": "productRecipeSet('Id%2026')",
		"type": "ZTS_MD_BP_SRV.ProductRecipe"
	}
}, {
	"ProductCode": "ProductCode 27",
	"SalesProgram": "SalesProgram 27",
	"DateFrom": "/Date(1129967261000)/",
	"DateTo": "/Date(1391327261000)/",
	"RecipeNumber": 4959.78,
	"Id": "Id 27",
	"__metadata": {
		"uri": "productRecipeSet('Id%2027')",
		"type": "ZTS_MD_BP_SRV.ProductRecipe"
	}
}, {
	"ProductCode": "ProductCode 28",
	"SalesProgram": "SalesProgram 28",
	"DateFrom": "/Date(1459669661000)/",
	"DateTo": "/Date(1101541661000)/",
	"RecipeNumber": 4626.93,
	"Id": "Id 28",
	"__metadata": {
		"uri": "productRecipeSet('Id%2028')",
		"type": "ZTS_MD_BP_SRV.ProductRecipe"
	}
}, {
	"ProductCode": "ProductCode 29",
	"SalesProgram": "SalesProgram 29",
	"DateFrom": "/Date(1301557661000)/",
	"DateTo": "/Date(1127980061000)/",
	"RecipeNumber": 8444.52,
	"Id": "Id 29",
	"__metadata": {
		"uri": "productRecipeSet('Id%2029')",
		"type": "ZTS_MD_BP_SRV.ProductRecipe"
	}
}, {
	"ProductCode": "ProductCode 30",
	"SalesProgram": "SalesProgram 30",
	"DateFrom": "/Date(1138520861000)/",
	"DateTo": "/Date(1103183261000)/",
	"RecipeNumber": 3065.86,
	"Id": "Id 30",
	"__metadata": {
		"uri": "productRecipeSet('Id%2030')",
		"type": "ZTS_MD_BP_SRV.ProductRecipe"
	}
}, {
	"ProductCode": "ProductCode 31",
	"SalesProgram": "SalesProgram 31",
	"DateFrom": "/Date(1090568862000)/",
	"DateTo": "/Date(1524296862000)/",
	"RecipeNumber": 4573.08,
	"Id": "Id 31",
	"__metadata": {
		"uri": "productRecipeSet('Id%2031')",
		"type": "ZTS_MD_BP_SRV.ProductRecipe"
	}
}, {
	"ProductCode": "ProductCode 32",
	"SalesProgram": "SalesProgram 32",
	"DateFrom": "/Date(961660062000)/",
	"DateTo": "/Date(1261986462000)/",
	"RecipeNumber": 1009.42,
	"Id": "Id 32",
	"__metadata": {
		"uri": "productRecipeSet('Id%2032')",
		"type": "ZTS_MD_BP_SRV.ProductRecipe"
	}
}, {
	"ProductCode": "ProductCode 33",
	"SalesProgram": "SalesProgram 33",
	"DateFrom": "/Date(1435909662000)/",
	"DateTo": "/Date(1439106462000)/",
	"RecipeNumber": 9656.82,
	"Id": "Id 33",
	"__metadata": {
		"uri": "productRecipeSet('Id%2033')",
		"type": "ZTS_MD_BP_SRV.ProductRecipe"
	}
}, {
	"ProductCode": "ProductCode 34",
	"SalesProgram": "SalesProgram 34",
	"DateFrom": "/Date(1092469662000)/",
	"DateTo": "/Date(1364888862000)/",
	"RecipeNumber": 1165.52,
	"Id": "Id 34",
	"__metadata": {
		"uri": "productRecipeSet('Id%2034')",
		"type": "ZTS_MD_BP_SRV.ProductRecipe"
	}
}, {
	"ProductCode": "ProductCode 35",
	"SalesProgram": "SalesProgram 35",
	"DateFrom": "/Date(1277106462000)/",
	"DateTo": "/Date(1474616862000)/",
	"RecipeNumber": 3599.42,
	"Id": "Id 35",
	"__metadata": {
		"uri": "productRecipeSet('Id%2035')",
		"type": "ZTS_MD_BP_SRV.ProductRecipe"
	}
}, {
	"ProductCode": "ProductCode 36",
	"SalesProgram": "SalesProgram 36",
	"DateFrom": "/Date(1083397662000)/",
	"DateTo": "/Date(1239090462000)/",
	"RecipeNumber": 6436.25,
	"Id": "Id 36",
	"__metadata": {
		"uri": "productRecipeSet('Id%2036')",
		"type": "ZTS_MD_BP_SRV.ProductRecipe"
	}
}, {
	"ProductCode": "ProductCode 37",
	"SalesProgram": "SalesProgram 37",
	"DateFrom": "/Date(1556092062000)/",
	"DateTo": "/Date(1363160862000)/",
	"RecipeNumber": 4953.57,
	"Id": "Id 37",
	"__metadata": {
		"uri": "productRecipeSet('Id%2037')",
		"type": "ZTS_MD_BP_SRV.ProductRecipe"
	}
}, {
	"ProductCode": "ProductCode 38",
	"SalesProgram": "SalesProgram 38",
	"DateFrom": "/Date(1501055262000)/",
	"DateTo": "/Date(1026200862000)/",
	"RecipeNumber": 1241.76,
	"Id": "Id 38",
	"__metadata": {
		"uri": "productRecipeSet('Id%2038')",
		"type": "ZTS_MD_BP_SRV.ProductRecipe"
	}
}, {
	"ProductCode": "ProductCode 39",
	"SalesProgram": "SalesProgram 39",
	"DateFrom": "/Date(1165909662000)/",
	"DateTo": "/Date(1388216862000)/",
	"RecipeNumber": 735.57,
	"Id": "Id 39",
	"__metadata": {
		"uri": "productRecipeSet('Id%2039')",
		"type": "ZTS_MD_BP_SRV.ProductRecipe"
	}
}, {
	"ProductCode": "ProductCode 40",
	"SalesProgram": "SalesProgram 40",
	"DateFrom": "/Date(965980062000)/",
	"DateTo": "/Date(1539244062000)/",
	"RecipeNumber": 8326.82,
	"Id": "Id 40",
	"__metadata": {
		"uri": "productRecipeSet('Id%2040')",
		"type": "ZTS_MD_BP_SRV.ProductRecipe"
	}
}]